Metadata-Version: 1.0
Name: faspell
Version: 0.1.1
Summary: Persian Spell_Checker in Python
Home-page: https://github.com/eteamin/faspell
Author: eteamin
Author-email: aminetesamian1371@gmail.com
License: UNKNOWN
Platform: UNKNOWN
